mobileprovision/__init__.py
mobileprovision/parser.py
mobileprovision/util.py
Py2MobileProvision-0.3.3.dist-info/LICENSE
Py2MobileProvision-0.3.3.dist-info/METADATA
Py2MobileProvision-0.3.3.dist-info/WHEEL
Py2MobileProvision-0.3.3.dist-info/top_level.txt
Py2MobileProvision-0.3.3.dist-info/RECORD
