Metadata-Version: 2.1
Name: Py2MobileProvision
Version: 0.3.3
Summary: Python2, parse ".mobileprovision" file in MacOS System;
Home-page: https://github.com/shede333/Py2MobileProvision
Author: shede333
Author-email: 333wshw@163.com
License: UNKNOWN
Keywords: mobileprovision mobile provision MobileProvision
Platform: UNKNOWN
Classifier: Development Status :: 4 - Beta
Classifier: Natural Language :: Chinese (Simplified)
Classifier: License :: OSI Approved :: MIT License
Classifier: Operating System :: MacOS :: MacOS X
Classifier: Operating System :: POSIX
Classifier: Programming Language :: Python
Classifier: Programming Language :: Python :: 2
Classifier: Programming Language :: Python :: 2.6
Classifier: Programming Language :: Python :: 2.7
Requires-Python: ~=2.6
